venvdotapp.py
venvdotapp-19.7.1.dist-info/entry_points.txt
venvdotapp-19.7.1.dist-info/WHEEL
venvdotapp-19.7.1.dist-info/METADATA
venvdotapp-19.7.1.dist-info/RECORD
