Metadata-Version: 1.1
Name: venvdotapp
Version: 19.7.1
Summary: Transform a virtual environment into a valid `.app` so that it can do .app-y
Home-page: https://github.com/glyph/venvdotapp
Author: Glyph
Author-email: glyph@twistedmatrix.com
